tc.py
simple_toolchain-1.0.1.dist-info/licenses/LICENSE
simple_toolchain-1.0.1.dist-info/METADATA
simple_toolchain-1.0.1.dist-info/WHEEL
simple_toolchain-1.0.1.dist-info/entry_points.txt
simple_toolchain-1.0.1.dist-info/top_level.txt
simple_toolchain-1.0.1.dist-info/RECORD
