Metadata-Version: 2.4
Name: simple-toolchain
Version: 1.0.1
Summary: A simple command line utility to manage Python scripts and single-file web apps with automatic dependency isolation
License: MIT
Project-URL: Homepage, https://github.com/yourusername/simple-toolchain
Project-URL: Bug Reports, https://github.com/yourusername/simple-toolchain/issues
Project-URL: Source, https://github.com/yourusername/simple-toolchain
Keywords: scripts,tools,cli,dependency-isolation,uv
Classifier: Development Status :: 5 - Production/Stable
Classifier: Intended Audience :: Developers
Classifier: Operating System :: OS Independent
Classifier: Programming Language :: Python :: 3
Classifier: Programming Language :: Python :: 3.7
Classifier: Programming Language :: Python :: 3.8
Classifier: Programming Language :: Python :: 3.9
Classifier: Programming Language :: Python :: 3.10
Classifier: Programming Language :: Python :: 3.11
Classifier: Programming Language :: Python :: 3.12
Classifier: Topic :: Software Development :: Libraries :: Python Modules
Classifier: Topic :: Utilities
Requires-Python: >=3.6
License-File: LICENSE
Dynamic: license-file
Dynamic: requires-python
